imio.events.core-1.2.45-py3.12-nspkg.pth
imio/events/core/__init__.py
imio/events/core/configure.zcml
imio/events/core/converters.py
imio/events/core/indexers.py
imio/events/core/indexers.zcml
imio/events/core/interfaces.py
imio/events/core/overrides.zcml
imio/events/core/permissions.zcml
imio/events/core/profiles.zcml
imio/events/core/setuphandlers.py
imio/events/core/subscribers.py
imio/events/core/subscribers.zcml
imio/events/core/testing.py
imio/events/core/utils.py
imio/events/core/vocabularies.py
imio/events/core/vocabularies.zcml
imio/events/core/browser/__init__.py
imio/events/core/browser/actions.py
imio/events/core/browser/configure.zcml
imio/events/core/browser/forms.py
imio/events/core/browser/json_recurrence.py
imio/events/core/browser/utils.py
imio/events/core/browser/bring_event_into_agendas/__init__.py
imio/events/core/browser/bring_event_into_agendas/agendas.py
imio/events/core/browser/bring_event_into_agendas/configure.zcml
imio/events/core/browser/overrides/.gitkeep
imio/events/core/browser/static/.gitkeep
imio/events/core/contents/__init__.py
imio/events/core/contents/configure.zcml
imio/events/core/contents/agenda/__init__.py
imio/events/core/contents/agenda/configure.zcml
imio/events/core/contents/agenda/content.py
imio/events/core/contents/entity/__init__.py
imio/events/core/contents/entity/configure.zcml
imio/events/core/contents/entity/content.py
imio/events/core/contents/event/__init__.py
imio/events/core/contents/event/configure.zcml
imio/events/core/contents/event/content.py
imio/events/core/contents/event/serializer.py
imio/events/core/contents/event/view.pt
imio/events/core/contents/event/views.py
imio/events/core/contents/folder/__init__.py
imio/events/core/contents/folder/configure.zcml
imio/events/core/contents/folder/content.py
imio/events/core/faceted/config/events.xml
imio/events/core/profiles/default/browserlayer.xml
imio/events/core/profiles/default/catalog.xml
imio/events/core/profiles/default/contentrules.xml
imio_events_core-1.2.45.dist-info/licenses/LICENSE.GPL
imio_events_core-1.2.45.dist-info/licenses/LICENSE.rst
imio_events_core-1.2.45.dist-info/METADATA
imio_events_core-1.2.45.dist-info/WHEEL
imio_events_core-1.2.45.dist-info/namespace_packages.txt
imio_events_core-1.2.45.dist-info/top_level.txt
imio_events_core-1.2.45.dist-info/RECORD
